django_status_signal/__init__.py
django_status_signal/base.py
django_status_signal-0.0.2.data/data/README.md/README.md
django_status_signal-0.0.2.dist-info/LICENSE
django_status_signal-0.0.2.dist-info/METADATA
django_status_signal-0.0.2.dist-info/WHEEL
django_status_signal-0.0.2.dist-info/top_level.txt
django_status_signal-0.0.2.dist-info/RECORD
