Metadata-Version: 2.1
Name: django-status-signal
Version: 0.0.2
Summary: enhanced django signal which enable you to trigger a signal only if the model instance is in a certain status
Home-page: https://github.com/ramwin/django-status-signal
Author: Xiang Wang
Author-email: ramwin@qq.com
License: BSD-3-Clause
Keywords: django status signal django enhanced signal
Platform: UNKNOWN
Classifier: Development Status :: 3 - Alpha
Classifier: Intended Audience :: Developers
Classifier: Topic :: Software Development :: Build Tools
Classifier: License :: OSI Approved :: MIT License
Classifier: Programming Language :: Python :: 3
Classifier: Programming Language :: Python :: 3.3
Classifier: Programming Language :: Python :: 3.4
Classifier: Programming Language :: Python :: 3.5
Classifier: Programming Language :: Python :: 3.6
Classifier: Programming Language :: Python :: 3.7
Requires-Dist: django
